{
    "id": 1,
    "name": "Hello World",
    "width": 3,
    "height": 3,
    "tilesize": 32,
    "map_data": [
        [
            {
                "x": 0,
                "y": 0,
                "type": "lava"
            },
            {
                "x": 1,
                "y": 0,
                "type": "grass"
            },
            {
                "x": 2,
                "y": 0,
                "type": "lava"
            }
        ],
        [
            {
                "x": 0,
                "y": 1,
                "type": "grass"
            },
            {
                "x": 1,
                "y": 1,
                "type": "lava"
            },
            {
                "x": 2,
                "y": 1,
                "type": "grass"
            }
        ],
        [
            {
                "x": 0,
                "y": 2,
                "type": "lava"
            },
            {
                "x": 1,
                "y": 2,
                "type": "grass"
            },
            {
                "x": 2,
                "y": 2,
                "type": "lava"
            }
        ]
    ]
}
